{"_id": "34360966|None", "id": "34360966", "infons": {}, "passages": [{"infons": {"journal": "Int J Mol Sci. 2021 Jul 30;22(15):8196. doi: 10.3390/ijms22158196.", "year": "2021", "article-id_pmc": "PMC8347370", "type": "title", "authors": "Trudler D, Ghatak S, Lipton SA"}, "offset": 0, "text": "Emerging hiPSC Models for Drug Discovery in Neurodegenerative Diseases.", "sentences": [], "annotations": [{"id": "1", "infons": {"identifier": "MESH:D019636", "type": "Disease", "valid": true, "normalized": ["D019636"], "database": "ncbi_mesh", "normalized_id": "D019636", "biotype": "disease", "name": "Neurodegenerative Diseases", "accession": "@DISEASE_Neurodegenerative_Diseases"}, "text": "Neurodegenerative Diseases", "locations": [{"offset": 44, "length": 26}]}], "relations": []}, {"infons": {"type": "abstract"}, "offset": 72, "text": "Neurodegenerative diseases affect millions of people worldwide and are characterized by the chronic and progressive deterioration of neural function. Neurodegenerative diseases, such as Alzheimer's disease (AD), Parkinson's disease (PD), amyotrophic lateral sclerosis (ALS), and Huntington's disease (HD), represent a huge social and economic burden due to increasing prevalence in our aging society, severity of symptoms, and lack of effective disease-modifying therapies. This lack of effective treatments is partly due to a lack of reliable models. Modeling neurodegenerative diseases is difficult because of poor access to human samples (restricted in general to postmortem tissue) and limited knowledge of disease mechanisms in a human context. Animal models play an instrumental role in understanding these diseases but fail to comprehensively represent the full extent of disease due to critical differences between humans and other mammals. The advent of human-induced pluripotent stem cell (hiPSC) technology presents an advantageous system that complements animal models of neurodegenerative diseases. Coupled with advances in gene-editing technologies, hiPSC-derived neural cells from patients and healthy donors now allow disease modeling using human samples that can be used for drug discovery.", "sentences": [], "annotations": [{"id": "21", "infons": {"identifier": "MESH:D019636", "type": "Disease", "valid": true, "normalized": ["D019636"], "database": "ncbi_mesh", "normalized_id": "D019636", "biotype": "disease", "name": "Neurodegenerative Diseases", "accession": "@DISEASE_Neurodegenerative_Diseases"}, "text": "Neurodegenerative diseases", "locations": [{"offset": 72, "length": 26}]}, {"id": "22", "infons": {"identifier": "MESH:D003291", "type": "Disease", "valid": true, "normalized": ["D003291"], "database": "ncbi_mesh", "normalized_id": "D003291", "biotype": "disease", "name": "Conversion Disorder", "accession": "@DISEASE_Conversion_Disorder"}, "text": "deterioration of neural function", "locations": [{"offset": 188, "length": 32}]}, {"id": "23", "infons": {"identifier": "MESH:D019636", "type": "Disease", "valid": true, "normalized": ["D019636"], "database": "ncbi_mesh", "normalized_id": "D019636", "biotype": "disease", "name": "Neurodegenerative Diseases", "accession": "@DISEASE_Neurodegenerative_Diseases"}, "text": "Neurodegenerative diseases", "locations": [{"offset": 222, "length": 26}]}, {"id": "24", "infons": {"identifier": "MESH:D000544", "type": "Disease", "valid": true, "normalized": ["D000544"], "database": "ncbi_mesh", "normalized_id": "D000544", "biotype": "disease", "name": "Alzheimer Disease", "accession": "@DISEASE_Alzheimer_Disease"}, "text": "Alzheimer's disease", "locations": [{"offset": 258, "length": 19}]}, {"id": "25", "infons": {"identifier": "MESH:D000544", "type": "Disease", "valid": true, "normalized": ["D000544"], "database": "ncbi_mesh", "normalized_id": "D000544", "biotype": "disease", "name": "Alzheimer Disease", "accession": "@DISEASE_Alzheimer_Disease"}, "text": "AD", "locations": [{"offset": 279, "length": 2}]}, {"id": "26", "infons": {"identifier": "MESH:D010300", "type": "Disease", "valid": true, "normalized": ["D010300"], "database": "ncbi_mesh", "normalized_id": "D010300", "biotype": "disease", "name": "Parkinson Disease", "accession": "@DISEASE_Parkinson_Disease"}, "text": "Parkinson's disease", "locations": [{"offset": 284, "length": 19}]}, {"id": "27", "infons": {"identifier": "MESH:D010300", "type": "Disease", "valid": true, "normalized": ["D010300"], "database": "ncbi_mesh", "normalized_id": "D010300", "biotype": "disease", "name": "Parkinson Disease", "accession": "@DISEASE_Parkinson_Disease"}, "text": "PD", "locations": [{"offset": 305, "length": 2}]}, {"id": "28", "infons": {"identifier": "MESH:D000690", "type": "Disease", "valid": true, "normalized": ["D000690"], "database": "ncbi_mesh", "normalized_id": "D000690", "biotype": "disease", "name": "Amyotrophic Lateral Sclerosis", "accession": "@DISEASE_Amyotrophic_Lateral_Sclerosis"}, "text": "amyotrophic lateral sclerosis", "locations": [{"offset": 310, "length": 29}]}, {"id": "29", "infons": {"identifier": "MESH:D000690", "type": "Disease", "valid": true, "normalized": ["D000690"], "database": "ncbi_mesh", "normalized_id": "D000690", "biotype": "disease", "name": "Amyotrophic Lateral Sclerosis", "accession": "@DISEASE_Amyotrophic_Lateral_Sclerosis"}, "text": "ALS", "locations": [{"offset": 341, "length": 3}]}, {"id": "30", "infons": {"identifier": "MESH:D006816", "type": "Disease", "valid": true, "normalized": ["D006816"], "database": "ncbi_mesh", "normalized_id": "D006816", "biotype": "disease", "name": "Huntington Disease", "accession": "@DISEASE_Huntington_Disease"}, "text": "Huntington's disease", "locations": [{"offset": 351, "length": 20}]}, {"id": "31", "infons": {"identifier": "MESH:D006816", "type": "Disease", "valid": true, "normalized": ["D006816"], "database": "ncbi_mesh", "normalized_id": "D006816", "biotype": "disease", "name": "Huntington Disease", "accession": "@DISEASE_Huntington_Disease"}, "text": "HD", "locations": [{"offset": 373, "length": 2}]}, {"id": "32", "infons": {"identifier": "MESH:D019636", "type": "Disease", "valid": true, "normalized": ["D019636"], "database": "ncbi_mesh", "normalized_id": "D019636", "biotype": "disease", "name": "Neurodegenerative Diseases", "accession": "@DISEASE_Neurodegenerative_Diseases"}, "text": "neurodegenerative diseases", "locations": [{"offset": 633, "length": 26}]}, {"id": "33", "infons": {"identifier": "9606", "type": "Species", "valid": true, "normalized": [9606], "database": "ncbi_taxonomy", "normalized_id": 9606, "biotype": "species", "name": "9606", "accession": null}, "text": "human", "locations": [{"offset": 699, "length": 5}]}, {"id": "34", "infons": {"identifier": "9606", "type": "Species", "valid": true, "normalized": [9606], "database": "ncbi_taxonomy", "normalized_id": 9606, "biotype": "species", "name": "9606", "accession": null}, "text": "human", "locations": [{"offset": 807, "length": 5}]}, {"id": "35", "infons": {"identifier": "9606", "type": "Species", "valid": true, "normalized": [9606], "database": "ncbi_taxonomy", "normalized_id": 9606, "biotype": "species", "name": "9606", "accession": null}, "text": "humans", "locations": [{"offset": 995, "length": 6}]}, {"id": "36", "infons": {"identifier": "9606", "type": "Species", "valid": true, "normalized": [9606], "database": "ncbi_taxonomy", "normalized_id": 9606, "biotype": "species", "name": "9606", "accession": null}, "text": "human", "locations": [{"offset": 1035, "length": 5}]}, {"id": "37", "infons": {"identifier": "MESH:D019636", "type": "Disease", "valid": true, "normalized": ["D019636"], "database": "ncbi_mesh", "normalized_id": "D019636", "biotype": "disease", "name": "Neurodegenerative Diseases", "accession": "@DISEASE_Neurodegenerative_Diseases"}, "text": "neurodegenerative diseases", "locations": [{"offset": 1156, "length": 26}]}, {"id": "38", "infons": {"identifier": "9606", "type": "Species", "valid": true, "normalized": [9606], "database": "ncbi_taxonomy", "normalized_id": 9606, "biotype": "species", "name": "9606", "accession": null}, "text": "patients", "locations": [{"offset": 1268, "length": 8}]}, {"id": "39", "infons": {"identifier": "9606", "type": "Species", "valid": true, "normalized": [9606], "database": "ncbi_taxonomy", "normalized_id": 9606, "biotype": "species", "name": "9606", "accession": null}, "text": "human", "locations": [{"offset": 1329, "length": 5}]}], "relations": []}], "relations": [], "pmid": 34360966, "pmcid": null, "meta": {}, "date": "2021-07-30T00:00:00Z", "journal": "Int J Mol Sci", "authors": ["Trudler D", "Ghatak S", "Lipton SA"], "relations_display": []}
